fetools/__init__.py
fetools/alias.py
fetools/geomath.py
fetools/pof.py
fetools-1.4.2.dist-info/LICENSE.md
fetools-1.4.2.dist-info/METADATA
fetools-1.4.2.dist-info/WHEEL
fetools-1.4.2.dist-info/top_level.txt
fetools-1.4.2.dist-info/RECORD
