Metadata-Version: 2.1
Name: fetools
Version: 1.4.2
Summary: Python library for VATUSA FEs.
Home-page: https://github.com/cessnahat/fetools
License: MIT
Keywords: vatsim vrc vstars veram
Classifier: Programming Language :: Python :: 3 :: Only
Classifier: License :: OSI Approved :: MIT License
Classifier: Intended Audience :: Developers
Classifier: Natural Language :: English
Requires-Python: >=3.6, <4
License-File: LICENSE.md
